sage_frontend/__init__.py
sage_frontend/sage_server/__init__.py
sage_frontend/sage_server/main.py
intsage_frontend-1.0.0.dist-info/METADATA
intsage_frontend-1.0.0.dist-info/WHEEL
intsage_frontend-1.0.0.dist-info/entry_points.txt
intsage_frontend-1.0.0.dist-info/top_level.txt
intsage_frontend-1.0.0.dist-info/RECORD
