Metadata-Version: 2.4
Name: intsage-frontend
Version: 1.0.0
Summary: SAGE Framework - Web Frontend and Dashboard Interface
Author-email: IntelliStream Team <intellistream@outlook.com>
License: MIT
Project-URL: Homepage, https://github.com/intellistream/SAGE
Project-URL: Repository, https://github.com/intellistream/SAGE.git
Project-URL: Documentation, https://intellistream.github.io/SAGE-Pub/
Project-URL: Issues, https://github.com/intellistream/SAGE/issues
Keywords: ui,framework,intellistream,ai,web,dashboard,data,fastapi,visualization,frontend,sage,ml,angular
Classifier: Development Status :: 4 - Beta
Classifier: Intended Audience :: Developers
Classifier: Intended Audience :: Science/Research
Classifier: License :: OSI Approved :: MIT License
Classifier: Operating System :: OS Independent
Classifier: Programming Language :: Python :: 3
Classifier: Programming Language :: Python :: 3.10
Classifier: Programming Language :: Python :: 3.11
Classifier: Programming Language :: Python :: 3.12
Classifier: Topic :: Scientific/Engineering :: Artificial Intelligence
Classifier: Topic :: Software Development :: Libraries :: Python Modules
Classifier: Topic :: System :: Distributed Computing
Requires-Python: >=3.10
Requires-Dist: fastapi>=0.100.0
Requires-Dist: uvicorn[standard]>=0.23.0
Requires-Dist: websockets>=11.0
Requires-Dist: python-multipart>=0.0.6
Requires-Dist: python-jose[cryptography]>=3.3.0
Requires-Dist: passlib[bcrypt]>=1.7.4
Requires-Dist: python-dotenv>=1.0.0
Requires-Dist: pydantic[email]>=2.0.0
Requires-Dist: pydantic-settings>=2.0.0
Requires-Dist: configparser>=5.3.0
Requires-Dist: PyYAML>=6.0
Requires-Dist: pandas>=2.0.0
Requires-Dist: numpy>=1.24.0
Requires-Dist: aiofiles>=23.0.0
Requires-Dist: python-multipart>=0.0.6
Requires-Dist: structlog>=23.0.0
Requires-Dist: rich>=13.0.0
Provides-Extra: sage
Requires-Dist: sage-kernel>=1.0.0; extra == "sage"
Requires-Dist: sage-middleware>=1.0.0; extra == "sage"
Requires-Dist: sage-userspace>=1.0.0; extra == "sage"
Provides-Extra: dev
Requires-Dist: pytest>=7.4.0; extra == "dev"
Requires-Dist: pytest-asyncio>=0.21.0; extra == "dev"
Requires-Dist: pytest-cov>=4.1.0; extra == "dev"
Requires-Dist: httpx>=0.24.0; extra == "dev"
Requires-Dist: black>=23.0.0; extra == "dev"
Requires-Dist: isort>=5.12.0; extra == "dev"
Requires-Dist: mypy>=1.0.0; extra == "dev"
Requires-Dist: ruff>=0.1.0; extra == "dev"
Requires-Dist: pre-commit>=3.0.0; extra == "dev"
Provides-Extra: visualization
Requires-Dist: plotly>=5.15.0; extra == "visualization"
Requires-Dist: dash>=2.11.0; extra == "visualization"
Requires-Dist: streamlit>=1.25.0; extra == "visualization"
Requires-Dist: matplotlib>=3.7.0; extra == "visualization"
Requires-Dist: seaborn>=0.12.0; extra == "visualization"
Provides-Extra: security
Requires-Dist: cryptography>=41.0.0; extra == "security"
Requires-Dist: bcrypt>=4.0.0; extra == "security"
Requires-Dist: authlib>=1.2.0; extra == "security"
Provides-Extra: monitoring
Requires-Dist: prometheus-client>=0.17.0; extra == "monitoring"
Requires-Dist: psutil>=5.9.0; extra == "monitoring"
Requires-Dist: memory-profiler>=0.61.0; extra == "monitoring"
